domainr_mcp_server/__init__.py
domainr_mcp_server/server.py
domainr_mcp_server-0.1.2.dist-info/licenses/LICENSE
domainr_mcp_server-0.1.2.dist-info/METADATA
domainr_mcp_server-0.1.2.dist-info/WHEEL
domainr_mcp_server-0.1.2.dist-info/entry_points.txt
domainr_mcp_server-0.1.2.dist-info/top_level.txt
domainr_mcp_server-0.1.2.dist-info/RECORD
