Metadata-Version: 2.4
Name: domainr-mcp-server
Version: 0.1.2
Summary: MCP server for Domainr domain search and availability checking
Author-email: Daniel Ohnesorge <82357071+danohn@users.noreply.github.com>
License: MIT
Project-URL: Homepage, https://github.com/danohn/domainr-mcp-server
Project-URL: Repository, https://github.com/danohn/domainr-mcp-server
Project-URL: Issues, https://github.com/danohn/domainr-mcp-server/issues
Classifier: Development Status :: 4 - Beta
Classifier: Intended Audience :: Developers
Classifier: License :: OSI Approved :: MIT License
Classifier: Operating System :: OS Independent
Classifier: Programming Language :: Python :: 3
Classifier: Programming Language :: Python :: 3.8
Classifier: Programming Language :: Python :: 3.9
Classifier: Programming Language :: Python :: 3.10
Classifier: Programming Language :: Python :: 3.11
Classifier: Programming Language :: Python :: 3.12
Requires-Python: >=3.8
License-File: LICENSE
Requires-Dist: mcp>=1.9.4
Requires-Dist: httpx>=0.28.1
Provides-Extra: dev
Requires-Dist: pytest>=7.0.0; extra == "dev"
Requires-Dist: pytest-asyncio>=0.21.0; extra == "dev"
Requires-Dist: pytest-httpx>=0.21.0; extra == "dev"
Requires-Dist: pytest-cov>=4.0.0; extra == "dev"
Requires-Dist: black>=23.0.0; extra == "dev"
Requires-Dist: isort>=5.12.0; extra == "dev"
Requires-Dist: flake8>=6.0.0; extra == "dev"
Requires-Dist: mypy>=1.0.0; extra == "dev"
Dynamic: license-file
